[
  {
    "p": [
      32,
      11,
      37,
      30,
      23,
      22,
      19,
      18,
      16,
      15,
      10,
      9
    ],
    "s": "D"
  },
  {
    "p": [
      16
    ],
    "s": "DAMAGED"
  },
  {
    "p": [
      4
    ],
    "s": "DARK"
  },
  {
    "p": [
      16
    ],
    "s": "DASHBOARD"
  },
  {
    "p": [
      19,
      47,
      32
    ],
    "s": "DATA"
  },
  {
    "p": [
      19
    ],
    "s": "DATABASE"
  },
  {
    "p": [
      20,
      46,
      28,
      3
    ],
    "s": "DATE"
  },
  {
    "p": [
      20
    ],
    "s": "DAY"
  },
  {
    "p": [
      26,
      9
    ],
    "s": "DAYS"
  },
  {
    "p": [
      32
    ],
    "s": "DEALING"
  },
  {
    "p": [
      15
    ],
    "s": "DECIDE"
  },
  {
    "p": [
      16
    ],
    "s": "DECREASE"
  },
  {
    "p": [
      16
    ],
    "s": "DEDICATED"
  },
  {
    "p": [
      16
    ],
    "s": "DEFAULT"
  },
  {
    "p": [
      32
    ],
    "s": "DEFINE"
  },
  {
    "p": [
      45
    ],
    "s": "DEFINED"
  },
  {
    "p": [
      30,
      22,
      37,
      25,
      19,
      12
    ],
    "s": "DELETE"
  },
  {
    "p": [
      16
    ],
    "s": "DELIVERABILITY"
  },
  {
    "p": [
      23,
      30,
      13,
      9
    ],
    "s": "DEMO"
  },
  {
    "p": [
      30
    ],
    "s": "DEMONSTRATION"
  },
  {
    "p": [
      15
    ],
    "s": "DENY"
  },
  {
    "p": [
      1
    ],
    "s": "DEPARTMENT"
  },
  {
    "p": [
      14,
      5,
      4
    ],
    "s": "DESCRIBES"
  },
  {
    "p": [
      32,
      46,
      43,
      42,
      23
    ],
    "s": "DESCRIPTION"
  },
  {
    "p": [
      47
    ],
    "s": "DESIGN"
  },
  {
    "p": [
      25,
      9
    ],
    "s": "DETAIL"
  },
  {
    "p": [
      8
    ],
    "s": "DETAILED"
  },
  {
    "p": [
      37,
      22,
      30,
      41,
      36,
      23,
      20,
      39,
      38,
      31,
      28,
      27,
      26,
      25,
      24,
      16,
      13,
      9
    ],
    "s": "DETAILS"
  },
  {
    "p": [
      45,
      28
    ],
    "s": "DETERMINE"
  },
  {
    "p": [
      1
    ],
    "s": "DEVELOPED"
  },
  {
    "p": [
      18
    ],
    "s": "DEVELOPER"
  },
  {
    "p": [
      7,
      10,
      6,
      1
    ],
    "s": "DHS"
  },
  {
    "p": [
      25,
      23,
      35,
      34,
      29,
      21,
      11,
      10,
      9
    ],
    "s": "DIALOGUE"
  },
  {
    "p": [
      47
    ],
    "s": "DICTIONARY"
  },
  {
    "p": [
      15
    ],
    "s": "DIFFERENT"
  },
  {
    "p": [
      47,
      16
    ],
    "s": "DIFFICULT"
  },
  {
    "p": [
      25
    ],
    "s": "DIRECT"
  },
  {
    "p": [
      4
    ],
    "s": "DIRECTED"
  },
  {
    "p": [
      32,
      13
    ],
    "s": "DIRECTLY"
  },
  {
    "p": [
      32,
      18
    ],
    "s": "DIRECTORY"
  },
  {
    "p": [
      41
    ],
    "s": "DIRECTS"
  },
  {
    "p": [
      37
    ],
    "s": "DISABLE"
  },
  {
    "p": [
      15
    ],
    "s": "DISCOVERED"
  },
  {
    "p": [
      32,
      23,
      4
    ],
    "s": "DISPLAY"
  },
  {
    "p": [
      31,
      16,
      9
    ],
    "s": "DISPLAYED"
  },
  {
    "p": [
      26,
      24,
      4
    ],
    "s": "DISPLAYS"
  },
  {
    "p": [
      18
    ],
    "s": "DIST"
  },
  {
    "p": [
      2
    ],
    "s": "DISTRIBUTION"
  },
  {
    "p": [
      16
    ],
    "s": "DKIM"
  },
  {
    "p": [
      18,
      20,
      17,
      4
    ],
    "s": "DM"
  },
  {
    "p": [
      3
    ],
    "s": "DMT"
  },
  {
    "p": [
      25,
      16,
      11,
      45,
      10,
      24,
      47,
      12,
      9,
      8,
      3,
      2
    ],
    "s": "DNS"
  },
  {
    "p": [
      17,
      16,
      15
    ],
    "s": "DO"
  },
  {
    "p": [
      46
    ],
    "s": "DOCUMENT"
  },
  {
    "p": [
      25
    ],
    "s": "DOES"
  },
  {
    "p": [
      11,
      10,
      9
    ],
    "s": "DOESN"
  },
  {
    "p": [
      9
    ],
    "s": "DOESN'T"
  },
  {
    "p": [
      11,
      10
    ],
    "s": "DOESN\u2019T"
  },
  {
    "p": [
      16,
      15,
      10,
      9,
      11,
      22,
      32,
      25,
      19,
      3,
      26,
      21,
      20,
      27,
      24,
      23,
      18,
      7,
      5,
      2,
      17,
      8,
      46,
      6,
      45,
      36,
      31,
      13,
      14,
      4,
      1
    ],
    "s": "DOMAIN"
  },
  {
    "p": [
      16,
      26,
      24,
      20,
      10,
      9
    ],
    "s": "DOMAIN'S"
  },
  {
    "p": [
      21
    ],
    "s": "DOMAIN(S"
  },
  {
    "p": [
      32
    ],
    "s": "DOMAIN-MANAGER-TEMPLATES"
  },
  {
    "p": [
      11
    ],
    "s": "DOMAIN-NAME"
  },
  {
    "p": [
      20,
      31,
      3,
      21,
      15,
      12,
      33,
      25,
      2,
      45,
      34,
      30,
      28,
      27,
      26,
      22,
      19,
      16,
      11,
      10,
      9
    ],
    "s": "DOMAINS"
  },
  {
    "p": [
      15,
      9,
      25
    ],
    "s": "DOMAIN\u2019S"
  },
  {
    "p": [
      32,
      16,
      7
    ],
    "s": "DON"
  },
  {
    "p": [
      16,
      7
    ],
    "s": "DON'T"
  },
  {
    "p": [
      25,
      17,
      8
    ],
    "s": "DONE"
  },
  {
    "p": [
      32
    ],
    "s": "DON\u2019T"
  },
  {
    "p": [
      17
    ],
    "s": "DOUBLES"
  },
  {
    "p": [
      27,
      22,
      2
    ],
    "s": "DOWN"
  },
  {
    "p": [
      32,
      31,
      44,
      30,
      29,
      23,
      22,
      12
    ],
    "s": "DOWNLOAD"
  },
  {
    "p": [
      9,
      7,
      26
    ],
    "s": "DROPDOWN"
  },
  {
    "p": [
      32
    ],
    "s": "DYNAMIC"
  }
]
